aiohttp_jwt/__init__.py
aiohttp_jwt/middleware.py
aiohttp_jwt/permissions.py
aiohttp_jwt/utils.py
aiohttp_jwt-0.6.1.dist-info/LICENSE.txt
aiohttp_jwt-0.6.1.dist-info/METADATA
aiohttp_jwt-0.6.1.dist-info/WHEEL
aiohttp_jwt-0.6.1.dist-info/top_level.txt
aiohttp_jwt-0.6.1.dist-info/RECORD
