Metadata-Version: 2.1
Name: aiohttp-jwt
Version: 0.6.1
Summary: aiohttp middleware for working with JWT
Home-page: https://github.com/hzlmn/aiohttp-jwt
Author: Oleh Kuchuk
Author-email: kuchuklehjs@gmail.com
License: MIT
Keywords: asyncio,aiohttp,jwt
Platform: UNKNOWN
Classifier: Intended Audience :: Developers
Classifier: License :: OSI Approved :: MIT License
Classifier: Programming Language :: Python
Classifier: Programming Language :: Python :: 3.6
